{
  "appPageId" : "096001b9-ecfe-4dac-ac87-54995fac471f",
  "componentName" : "community_layout:sldsFlexibleLayout",
  "id" : "e40f59ea-b085-46c3-bf27-650fb136c545",
  "label" : "Too Many Requests",
  "regions" : [ {
    "components" : [ {
      "componentAttributes" : {
        "backgroundImageConfig" : "",
        "backgroundImageOverlay" : "rgba(0,0,0,0)",
        "sectionConfig" : "{\"UUID\":\"ced018ef-f4db-4088-82f6-c6a705f1e968\",\"columns\":[{\"UUID\":\"b171eccb-bc4a-498d-b824-92df219acd7b\",\"columnName\":\"Column 1\",\"columnKey\":\"col1\",\"columnWidth\":\"12\",\"seedComponents\":null}]}"
      },
      "componentName" : "community_layout:section",
      "id" : "ced018ef-f4db-4088-82f6-c6a705f1e968",
      "regions" : [ {
        "components" : [ {
          "componentAttributes" : {
            "richTextValue" : "<div style=\"display: flex; align-items: center; flex-direction: column; margin: 60px 25px 30px 25px;\">\n\t<div style=\"background-image: url(assets/img/tooManyRequests.svg); background-size: contain; height: 350px; width: 100%; background-repeat: no-repeat; background-position: center;\"></div>\n</div>\n<div style=\"margin: 0 25px; text-align: center;\">\n\t<h1 class=\"slds-text-heading_large\">Looks like the site is experiencing higher than usual demand&#8230;</h1>\n\t<p class=\"slds-text-heading_small\">Don't go anywhere. We'll redirect you in a moment.</p>\n</div>"
          },
          "componentName" : "community_builder:htmlEditor",
          "id" : "9f0ca705-a58d-4aef-8d8b-b4b6125d0342",
          "renderPriority" : "NEUTRAL",
          "renditionMap" : { },
          "type" : "component"
        }, {
          "componentAttributes" : { },
          "componentName" : "experience_availability:autoRefresh",
          "id" : "eac26e88-30a9-4b31-8904-61a9c4bc3507",
          "renderPriority" : "NEUTRAL",
          "renditionMap" : { },
          "type" : "component"
        } ],
        "id" : "b171eccb-bc4a-498d-b824-92df219acd7b",
        "regionLabel" : "Column 1",
        "regionName" : "col1",
        "renditionMap" : { },
        "type" : "region"
      } ],
      "renderPriority" : "NEUTRAL",
      "renditionMap" : { },
      "scopedBrandingSetId" : null,
      "type" : "component"
    } ],
    "id" : "b4eabbd7-7b7c-4698-8df5-870e7350f35e",
    "regionName" : "content",
    "type" : "region"
  } ],
  "themeLayoutType" : "ServiceNotAvailable",
  "type" : "view",
  "viewType" : "too-many-requests"
}